anm_addit/__init__.py
anm_addit/main.py
anm_addit-0.0.3.dist-info/METADATA
anm_addit-0.0.3.dist-info/WHEEL
anm_addit-0.0.3.dist-info/top_level.txt
anm_addit-0.0.3.dist-info/RECORD
