Metadata-Version: 2.1
Name: anm-addit
Version: 0.0.3
Author: Anshuman Mishra
